{
	"backtrace" : 6,
	"backtraceGraph" : 
	{
		"commands" : 
		[
			"add_custom_target",
			"_qt_internal_qml_type_registration",
			"qt6_add_qml_module",
			"qt_add_qml_module",
			"include",
			"add_dependencies"
		],
		"files" : 
		[
			"C:/Qt/6.7.2/mingw_64/lib/cmake/Qt6Qml/Qt6QmlMacros.cmake",
			"qmlmodules",
			"CMakeLists.txt",
			"content/CMakeLists.txt",
			"imports/PocketDemo/CMakeLists.txt",
			"imports/ComponentBundles/MaterialBundle/CMakeLists.txt",
			"imports/QtQuick/Studio/Application/CMakeLists.txt",
			"imports/QtQuick/Studio/Components/CMakeLists.txt"
		],
		"nodes" : 
		[
			{
				"file" : 2
			},
			{
				"command" : 4,
				"file" : 2,
				"line" : 32,
				"parent" : 0
			},
			{
				"file" : 1,
				"parent" : 1
			},
			{
				"command" : 3,
				"file" : 1,
				"line" : 1,
				"parent" : 2
			},
			{
				"command" : 2,
				"file" : 0,
				"line" : 780,
				"parent" : 3
			},
			{
				"command" : 1,
				"file" : 0,
				"line" : 541,
				"parent" : 4
			},
			{
				"command" : 0,
				"file" : 0,
				"line" : 3046,
				"parent" : 5
			},
			{
				"command" : 5,
				"file" : 0,
				"line" : 3049,
				"parent" : 5
			},
			{
				"file" : 3
			},
			{
				"command" : 3,
				"file" : 3,
				"line" : 3,
				"parent" : 8
			},
			{
				"command" : 2,
				"file" : 0,
				"line" : 780,
				"parent" : 9
			},
			{
				"command" : 1,
				"file" : 0,
				"line" : 541,
				"parent" : 10
			},
			{
				"command" : 5,
				"file" : 0,
				"line" : 3049,
				"parent" : 11
			},
			{
				"file" : 4
			},
			{
				"command" : 3,
				"file" : 4,
				"line" : 7,
				"parent" : 13
			},
			{
				"command" : 2,
				"file" : 0,
				"line" : 780,
				"parent" : 14
			},
			{
				"command" : 1,
				"file" : 0,
				"line" : 541,
				"parent" : 15
			},
			{
				"command" : 5,
				"file" : 0,
				"line" : 3049,
				"parent" : 16
			},
			{
				"file" : 5
			},
			{
				"command" : 3,
				"file" : 5,
				"line" : 2,
				"parent" : 18
			},
			{
				"command" : 2,
				"file" : 0,
				"line" : 780,
				"parent" : 19
			},
			{
				"command" : 1,
				"file" : 0,
				"line" : 541,
				"parent" : 20
			},
			{
				"command" : 5,
				"file" : 0,
				"line" : 3049,
				"parent" : 21
			},
			{
				"file" : 6
			},
			{
				"command" : 3,
				"file" : 6,
				"line" : 8,
				"parent" : 23
			},
			{
				"command" : 2,
				"file" : 0,
				"line" : 780,
				"parent" : 24
			},
			{
				"command" : 1,
				"file" : 0,
				"line" : 541,
				"parent" : 25
			},
			{
				"command" : 5,
				"file" : 0,
				"line" : 3049,
				"parent" : 26
			},
			{
				"file" : 7
			},
			{
				"command" : 3,
				"file" : 7,
				"line" : 6,
				"parent" : 28
			},
			{
				"command" : 2,
				"file" : 0,
				"line" : 780,
				"parent" : 29
			},
			{
				"command" : 1,
				"file" : 0,
				"line" : 541,
				"parent" : 30
			},
			{
				"command" : 5,
				"file" : 0,
				"line" : 3049,
				"parent" : 31
			}
		]
	},
	"dependencies" : 
	[
		{
			"backtrace" : 7,
			"id" : "FxMaterialShowroomApp_qmltyperegistration::@6890427a1f51a3e7e1df"
		},
		{
			"backtrace" : 12,
			"id" : "FXMaterialShowroomContent_qmltyperegistration::@73a38b9e525c9c2ae262"
		},
		{
			"backtrace" : 17,
			"id" : "PocketDemo_qmltyperegistration::@396c3568c859ee729b08"
		},
		{
			"backtrace" : 22,
			"id" : "CB_MaterialBundle_qmltyperegistration::@82ceb79724bbf5de351a"
		},
		{
			"backtrace" : 27,
			"id" : "QQS_App_qmltyperegistration::@467dac7d6c3792bf8fb2"
		},
		{
			"backtrace" : 32,
			"id" : "QQS_Components_qmltyperegistration::@92bfa96da900ff03600e"
		}
	],
	"folder" : 
	{
		"name" : "QtInternalTargets"
	},
	"id" : "all_qmltyperegistrations::@6890427a1f51a3e7e1df",
	"name" : "all_qmltyperegistrations",
	"paths" : 
	{
		"build" : ".",
		"source" : "."
	},
	"sources" : [],
	"type" : "UTILITY"
}
